pytest_django_filefield/__init__.py
pytest_django_filefield/plugin.py
pytest_django_filefield-0.1.2.dist-info/entry_points.txt
pytest_django_filefield-0.1.2.dist-info/WHEEL
pytest_django_filefield-0.1.2.dist-info/METADATA
pytest_django_filefield-0.1.2.dist-info/RECORD
