Metadata-Version: 2.1
Name: pytest-django-filefield
Version: 0.1.2
Summary: Replaces FileField.storage with something you can patch globally.
Author-email: Mikhail Bulash <scaryspiderpig@protonmail.com>
Classifier: Development Status :: 5 - Production/Stable
Classifier: Framework :: Django
Classifier: Intended Audience :: Developers
Classifier: License :: OSI Approved :: The Unlicense (Unlicense)
Classifier: Operating System :: OS Independent
Classifier: Programming Language :: Python
Classifier: Topic :: Software Development :: Testing
Requires-Dist: pytest >= 5.2
